AUTHORS
CHANGES
LICENSE
MANIFEST.in
Makefile
README
setup.cfg
setup.py
bulbs/__init__.py
bulbs/config.py
bulbs/element.py
bulbs/factory.py
bulbs/gremlin.groovy
bulbs/gremlin.py
bulbs/groovy.py
bulbs/json.py
bulbs/model.py
bulbs/property.py
bulbs/registry.py
bulbs/rest.py
bulbs/utils.py
bulbs/yaml.py
bulbs.egg-info/PKG-INFO
bulbs.egg-info/SOURCES.txt
bulbs.egg-info/dependency_links.txt
bulbs.egg-info/not-zip-safe
bulbs.egg-info/requires.txt
bulbs.egg-info/top_level.txt
bulbs/base/__init__.py
bulbs/base/client.py
bulbs/base/graph.py
bulbs/base/index.py
bulbs/base/typesystem.py
bulbs/neo4jserver/__init__.py
bulbs/neo4jserver/batch.py
bulbs/neo4jserver/client.py
bulbs/neo4jserver/cypher.py
bulbs/neo4jserver/cypher.yaml
bulbs/neo4jserver/graph.py
bulbs/neo4jserver/gremlin.groovy
bulbs/neo4jserver/index.py
bulbs/neo4jserver/tests/__init__.py
bulbs/neo4jserver/tests/bulbs_tests.py
bulbs/neo4jserver/tests/client_tests.py
bulbs/rexster/__init__.py
bulbs/rexster/batch.py
bulbs/rexster/client.py
bulbs/rexster/graph.py
bulbs/rexster/gremlin.groovy
bulbs/rexster/index.py
bulbs/rexster/tests/__init__.py
bulbs/rexster/tests/bulbs_tests.py
bulbs/rexster/tests/client_tests.py
bulbs/rexster/tests/index_tests.py
bulbs/tests/__init__.py
bulbs/tests/bulbs_tests.py
bulbs/tests/client_tests.py
bulbs/tests/element_tests.py
bulbs/tests/graph_tests.py
bulbs/tests/gremlin_tests.py
bulbs/tests/index_tests.py
bulbs/tests/model_tests.py
bulbs/tests/rest_tests.py
bulbs/tests/testcase.py
tests/bulbs_tests.py